topicModel/__init__.py
topicModel/cli.py
topicModel/config.py
topicModel/model.py
topicModel/preprocess.py
topicModel/stopwords.txt
topicModel/tool.py
pyunit_topicmodel-1.0.2.dist-info/LICENSE
pyunit_topicmodel-1.0.2.dist-info/METADATA
pyunit_topicmodel-1.0.2.dist-info/WHEEL
pyunit_topicmodel-1.0.2.dist-info/entry_points.txt
pyunit_topicmodel-1.0.2.dist-info/top_level.txt
pyunit_topicmodel-1.0.2.dist-info/RECORD
