Metadata-Version: 2.1
Name: pyunit-topicmodel
Version: 1.0.2
Summary: 主题识别模型
Home-page: https://github.com/pyunits/pyunits-topicmodel
Author: 张伟
Author-email: jtyoui@qq.com
License: MIT Licence
Platform: any
Classifier: Programming Language :: Python :: 3
Classifier: License :: OSI Approved :: MIT License
License-File: LICENSE
Requires-Dist: tqdm
Requires-Dist: pandas
Requires-Dist: matplotlib
Requires-Dist: gensim
Requires-Dist: jieba
Requires-Dist: nltk
Requires-Dist: openpyxl
